aext_assistant/__init__.py
aext_assistant-0.0.1.dist-info/METADATA
aext_assistant-0.0.1.dist-info/WHEEL
aext_assistant-0.0.1.dist-info/RECORD
